tldr.py
tldr-3.4.3.data/data/share/man/man1/tldr.1
tldr-3.4.3.dist-info/METADATA
tldr-3.4.3.dist-info/WHEEL
tldr-3.4.3.dist-info/entry_points.txt
tldr-3.4.3.dist-info/licenses/LICENSE.md
tldr-3.4.3.dist-info/RECORD
