Metadata-Version: 2.4
Name: tldr
Version: 3.4.3
Summary: Official Python command line client for tldr pages.
Project-URL: Homepage, https://tldr.sh
Project-URL: Source, https://github.com/tldr-pages/tldr-python-client
Project-URL: Issues, https://github.com/tldr-pages/tldr-python-client/issues
Project-URL: Changelog, https://github.com/tldr-pages/tldr-python-client/blob/main/CHANGELOG.md
Project-URL: Funding, https://liberapay.com/tldr-pages
Author: Felix Yan and tldr-pages contributors
License-Expression: MIT
License-File: LICENSE.md
Keywords: cheatsheets,documentation,man,manpages,tldr,tldr-pages
Classifier: Development Status :: 5 - Production/Stable
Classifier: Environment :: Console
Classifier: Intended Audience :: Developers
Classifier: Intended Audience :: Education
Classifier: Intended Audience :: End Users/Desktop
Classifier: License :: OSI Approved :: MIT License
Classifier: Natural Language :: English
Classifier: Operating System :: Android
Classifier: Operating System :: MacOS :: MacOS X
Classifier: Operating System :: Microsoft :: Windows
Classifier: Operating System :: POSIX
Classifier: Operating System :: POSIX :: BSD :: FreeBSD
Classifier: Operating System :: POSIX :: BSD :: NetBSD
Classifier: Operating System :: POSIX :: BSD :: OpenBSD
Classifier: Operating System :: POSIX :: Linux
Classifier: Operating System :: POSIX :: SunOS/Solaris
Classifier: Programming Language :: Python :: 3.9
Classifier: Programming Language :: Python :: 3.10
Classifier: Programming Language :: Python :: 3.11
Classifier: Programming Language :: Python :: 3.12
Classifier: Programming Language :: Python :: 3.13
Classifier: Topic :: Documentation
Classifier: Topic :: Software Development :: Documentation
Classifier: Topic :: System
Classifier: Topic :: Utilities
Requires-Python: ~=3.9
Requires-Dist: colorama==0.4.6; sys_platform == 'win32'
Requires-Dist: shtab>=1.3.10
Requires-Dist: termcolor
Provides-Extra: cli
Requires-Dist: flake8; extra == 'cli'
Requires-Dist: pytest; extra == 'cli'
Requires-Dist: pytest-runner; extra == 'cli'
Requires-Dist: sphinx; extra == 'cli'
Requires-Dist: sphinx-argparse; extra == 'cli'
